[
  {
    "shortDescription" : "",
    "metadataOutputVersion" : "3.0",
    "outputSchema" : [
      {
        "isOptional" : "0",
        "formattedType" : "String",
        "type" : "String",
        "name" : "label",
        "shortDescription" : "Text label"
      }
    ],
    "version" : "",
    "modelParameters" : [

    ],
    "author" : "Zayne",
    "specificationVersion" : 4,
    "license" : "",
    "isUpdatable" : "0",
    "availability" : {
      "macOS" : "10.15",
      "tvOS" : "13.0",
      "watchOS" : "6.0",
      "iOS" : "13.0",
      "macCatalyst" : "13.0"
    },
    "modelType" : {
      "name" : "MLModelType_textClassifier"
    },
    "inputSchema" : [
      {
        "isOptional" : "0",
        "formattedType" : "String",
        "type" : "String",
        "name" : "text",
        "shortDescription" : "Input text"
      }
    ],
    "classLabels" : [
      "politics",
      "sport",
      "business",
      "entertainment",
      "tech"
    ],
    "generatedClassName" : "DocumentClassifierDynamicEmbedding",
    "userDefinedMetadata" : {
      "com.apple.createml.app.tag" : "53.6",
      "com.apple.createml.version" : "11.6.0",
      "com.apple.coreml.model.preview.type" : "textClassifier",
      "com.apple.createml.app.version" : "2.0"
    },
    "method" : "predict"
  }
]